<mods xmlns:xlink="http://www.w3.org/1999/xlink" xmlns:xsi="http://www.w3.org/2001/XMLSchema-instance" xmlns="http://www.loc.gov/mods/v3" version="3.3" xsi:schemaLocation="http://www.loc.gov/mods/v3 http://www.loc.gov/standards/mods/v3/mods-3-3.xsd"><id>1781376</id><setSpec>journal_article</setSpec><setSpec>doc-type:article</setSpec><setSpec>ddc:530</setSpec><setSpec>journal_articleFtxt</setSpec><setSpec>open_access</setSpec>

<genre>article</genre>

<titleInfo><title>Hadronic production of J/Psi and Upsilon: transverse momentum distributions</title></titleInfo>


<note type="publicationStatus">published</note>



<name type="personal">
  <namePart type="given">Rudolf</namePart>
  <namePart type="family">Baier</namePart>
  <role><roleTerm type="text">author</roleTerm> </role><identifier type="local">40336</identifier></name>
<name type="personal">
  <namePart type="given">R.</namePart>
  <namePart type="family">Rückl</namePart>
  <role><roleTerm type="text">author</roleTerm> </role></name>







<name type="corporate">
  <namePart/>
  <identifier type="local">23470601</identifier>
  <role>
    <roleTerm type="text">department</roleTerm>
  </role>
</name>









<relatedItem type="constituent">
  <location>
    <url displayLabel="Baier_071.pdf">https://pub.uni-bielefeld.de/download/1781376/2313281/Baier_071.pdf</url>
  </location>
  <physicalDescription><internetMediaType>application/pdf</internetMediaType></physicalDescription>
  <accessCondition type="restrictionOnAccess">no</accessCondition>
</relatedItem>
<originInfo><publisher>Elsevier BV</publisher><dateIssued encoding="w3cdtf">1981</dateIssued>
</originInfo>
<language><languageTerm authority="iso639-2b" type="code">eng</languageTerm>
</language>



<relatedItem type="host"><titleInfo><title>Physics Letters B</title></titleInfo>
  <identifier type="issn">0370-2693</identifier>
  <identifier type="INSPIRE">164479</identifier>
  <identifier type="ISI">A1981LV92500015</identifier><identifier type="urn">urn:nbn:de:0070-pub-17813762</identifier><identifier type="doi">10.1016/0370-2693(81)90636-5</identifier>
<part><detail type="volume"><number>102</number></detail><detail type="issue"><number>5</number></detail><extent unit="pages">364-370</extent>
</part>
</relatedItem>


<extension>
<bibliographicCitation>
<ama>Baier R, Rückl R. Hadronic production of J/Psi and Upsilon: transverse momentum distributions. &lt;em&gt;Physics Letters B&lt;/em&gt;. 1981;102(5):364-370.</ama>
<chicago>&lt;div style="text-indent:-25px; padding-left:25px;padding-bottom:0px;"&gt;Baier, Rudolf, and Rückl, R. 1981. “Hadronic production of J/Psi and Upsilon: transverse momentum distributions”. &lt;em&gt;Physics Letters B&lt;/em&gt; 102 (5): 364-370.&lt;/div&gt;</chicago>
<lncs> Baier, R., Rückl, R.: Hadronic production of J/Psi and Upsilon: transverse momentum distributions. Physics Letters B. 102, 364-370 (1981).</lncs>
<dgps>&lt;div style="text-indent:-25px; padding-left:25px;padding-bottom:0px;"&gt;Baier, R. &amp;amp; Rückl, R. (1981). Hadronic production of J/Psi and Upsilon: transverse momentum distributions. &lt;em&gt;Physics Letters B&lt;/em&gt;, &lt;em&gt;102&lt;/em&gt;(5), 364-370. Elsevier BV. doi:10.1016/0370-2693(81)90636-5.&lt;/div&gt;</dgps>
<angewandte-chemie>R.  Baier, and R.  Rückl, “Hadronic production of J/Psi and Upsilon: transverse momentum distributions”, &lt;em&gt;Physics Letters B&lt;/em&gt;, &lt;strong&gt;1981&lt;/strong&gt;, &lt;em&gt;102&lt;/em&gt;, 364-370.</angewandte-chemie>
<bio1>Baier R, Rückl R (1981) &lt;br /&gt;Hadronic production of J/Psi and Upsilon: transverse momentum distributions.&lt;br /&gt;Physics Letters B 102(5): 364-370.</bio1>
<harvard1>Baier, R., &amp;amp; Rückl, R., 1981. Hadronic production of J/Psi and Upsilon: transverse momentum distributions. &lt;em&gt;Physics Letters B&lt;/em&gt;, 102(5), p 364-370.</harvard1>
<ieee> R. Baier and R. Rückl, “Hadronic production of J/Psi and Upsilon: transverse momentum distributions”, &lt;em&gt;Physics Letters B&lt;/em&gt;,  vol. 102, 1981,  pp. 364-370.</ieee>
<apa>Baier, R., &amp;amp; Rückl, R. (1981). Hadronic production of J/Psi and Upsilon: transverse momentum distributions. &lt;em&gt;Physics Letters B&lt;/em&gt;, &lt;em&gt;102&lt;/em&gt;(5), 364-370. &lt;a href="https://doi.org/10.1016/0370-2693(81)90636-5" target="_blank"&gt;https://doi.org/10.1016/0370-2693(81)90636-5&lt;/a&gt;</apa>
<wels>Baier, R.; Rückl, R. (1981): Hadronic production of J/Psi and Upsilon: transverse momentum distributions &lt;em&gt;Physics Letters B&lt;/em&gt;,102:(5): 364-370.</wels>
<apa_indent>&lt;div style="text-indent:-25px; padding-left:25px;padding-bottom:0px;"&gt;Baier, R., &amp;amp; Rückl, R. (1981). Hadronic production of J/Psi and Upsilon: transverse momentum distributions. &lt;em&gt;Physics Letters B&lt;/em&gt;, &lt;em&gt;102&lt;/em&gt;(5), 364-370. &lt;a href="https://doi.org/10.1016/0370-2693(81)90636-5" target="_blank"&gt;https://doi.org/10.1016/0370-2693(81)90636-5&lt;/a&gt;&lt;/div&gt;</apa_indent>
<mla>Baier, Rudolf, and Rückl, R. “Hadronic production of J/Psi and Upsilon: transverse momentum distributions”. &lt;em&gt;Physics Letters B&lt;/em&gt; 102.5 (1981): 364-370.</mla>
<frontiers>Baier, R., and Rückl, R. (1981). Hadronic production of J/Psi and Upsilon: transverse momentum distributions. &lt;em&gt;Physics Letters B&lt;/em&gt; 102, 364-370.</frontiers>
<default>Baier R, Rückl R (1981) &lt;br /&gt;&lt;em&gt;Physics Letters B&lt;/em&gt; 102(5): 364-370.</default>
</bibliographicCitation>
</extension>
<recordInfo><recordIdentifier>1781376</recordIdentifier><recordCreationDate encoding="w3cdtf">2018-07-24T12:59:16Z</recordCreationDate><recordChangeDate encoding="w3cdtf">2018-07-24T12:59:16Z</recordChangeDate>
</recordInfo>
</mods>