<mods xmlns:xlink="http://www.w3.org/1999/xlink" xmlns:xsi="http://www.w3.org/2001/XMLSchema-instance" xmlns="http://www.loc.gov/mods/v3" version="3.3" xsi:schemaLocation="http://www.loc.gov/mods/v3 http://www.loc.gov/standards/mods/v3/mods-3-3.xsd"><id>1782178</id><setSpec>journal_article</setSpec><setSpec>doc-type:article</setSpec><setSpec>ddc:510</setSpec><setSpec>journal_articleFtxt</setSpec><setSpec>open_access</setSpec>

<genre>article</genre>

<titleInfo><title>Heegaard-Zerlegungen der 3-Sphäre</title></titleInfo>


<note type="publicationStatus">published</note>



<name type="personal">
  <namePart type="given">Friedhelm</namePart>
  <namePart type="family">Waldhausen</namePart>
  <role><roleTerm type="text">author</roleTerm> </role><identifier type="local">10607</identifier></name>







<name type="corporate">
  <namePart/>
  <identifier type="local">10020</identifier>
  <role>
    <roleTerm type="text">department</roleTerm>
  </role>
</name>









<relatedItem type="constituent">
  <location>
    <url displayLabel="Waldhausen_020.pdf">https://pub.uni-bielefeld.de/download/1782178/2313707/Waldhausen_020.pdf</url>
  </location>
  <physicalDescription><internetMediaType>application/pdf</internetMediaType></physicalDescription>
  <accessCondition type="restrictionOnAccess">no</accessCondition>
</relatedItem>
<originInfo><publisher>Elsevier BV</publisher><dateIssued encoding="w3cdtf">1968</dateIssued>
</originInfo>
<language><languageTerm authority="iso639-2b" type="code">ger</languageTerm>
</language>



<relatedItem type="host"><titleInfo><title>Topology</title></titleInfo>
  <identifier type="issn">0040-9383</identifier><identifier type="urn">urn:nbn:de:0070-pub-17821780</identifier><identifier type="doi">10.1016/0040-9383(68)90027-X</identifier>
<part><detail type="volume"><number>7</number></detail><detail type="issue"><number>2</number></detail><extent unit="pages">195-203</extent>
</part>
</relatedItem>


<extension>
<bibliographicCitation>
<wels>Waldhausen, F. (1968): Heegaard-Zerlegungen der 3-Sphäre &lt;em&gt;Topology&lt;/em&gt;,7:(2): 195-203.</wels>
<bio1>Waldhausen F (1968) &lt;br /&gt;Heegaard-Zerlegungen der 3-Sphäre.&lt;br /&gt;Topology 7(2): 195-203.</bio1>
<harvard1>Waldhausen, F., 1968. Heegaard-Zerlegungen der 3-Sphäre. &lt;em&gt;Topology&lt;/em&gt;, 7(2), p 195-203.</harvard1>
<apa_indent>&lt;div style="text-indent:-25px; padding-left:25px;padding-bottom:0px;"&gt;Waldhausen, F. (1968). Heegaard-Zerlegungen der 3-Sphäre. &lt;em&gt;Topology&lt;/em&gt;, &lt;em&gt;7&lt;/em&gt;(2), 195-203. &lt;a href="https://doi.org/10.1016/0040-9383(68)90027-X" target="_blank"&gt;https://doi.org/10.1016/0040-9383(68)90027-X&lt;/a&gt;&lt;/div&gt;</apa_indent>
<angewandte-chemie>F.  Waldhausen, “Heegaard-Zerlegungen der 3-Sphäre”, &lt;em&gt;Topology&lt;/em&gt;, &lt;strong&gt;1968&lt;/strong&gt;, &lt;em&gt;7&lt;/em&gt;, 195-203.</angewandte-chemie>
<ama>Waldhausen F. Heegaard-Zerlegungen der 3-Sphäre. &lt;em&gt;Topology&lt;/em&gt;. 1968;7(2):195-203.</ama>
<frontiers>Waldhausen, F. (1968). Heegaard-Zerlegungen der 3-Sphäre. &lt;em&gt;Topology&lt;/em&gt; 7, 195-203.</frontiers>
<dgps>&lt;div style="text-indent:-25px; padding-left:25px;padding-bottom:0px;"&gt;Waldhausen, F. (1968). Heegaard-Zerlegungen der 3-Sphäre. &lt;em&gt;Topology&lt;/em&gt;, &lt;em&gt;7&lt;/em&gt;(2), 195-203. Elsevier BV. doi:10.1016/0040-9383(68)90027-X.&lt;/div&gt;</dgps>
<apa>Waldhausen, F. (1968). Heegaard-Zerlegungen der 3-Sphäre. &lt;em&gt;Topology&lt;/em&gt;, &lt;em&gt;7&lt;/em&gt;(2), 195-203. &lt;a href="https://doi.org/10.1016/0040-9383(68)90027-X" target="_blank"&gt;https://doi.org/10.1016/0040-9383(68)90027-X&lt;/a&gt;</apa>
<ieee> F. Waldhausen, “Heegaard-Zerlegungen der 3-Sphäre”, &lt;em&gt;Topology&lt;/em&gt;,  vol. 7, 1968,  pp. 195-203.</ieee>
<lncs> Waldhausen, F.: Heegaard-Zerlegungen der 3-Sphäre. Topology. 7, 195-203 (1968).</lncs>
<chicago>&lt;div style="text-indent:-25px; padding-left:25px;padding-bottom:0px;"&gt;Waldhausen, Friedhelm. 1968. “Heegaard-Zerlegungen der 3-Sphäre”. &lt;em&gt;Topology&lt;/em&gt; 7 (2): 195-203.&lt;/div&gt;</chicago>
<mla>Waldhausen, Friedhelm. “Heegaard-Zerlegungen der 3-Sphäre”. &lt;em&gt;Topology&lt;/em&gt; 7.2 (1968): 195-203.</mla>
<default>Waldhausen F (1968) &lt;br /&gt;&lt;em&gt;Topology&lt;/em&gt; 7(2): 195-203.</default>
</bibliographicCitation>
</extension>
<recordInfo><recordIdentifier>1782178</recordIdentifier><recordCreationDate encoding="w3cdtf">2018-07-24T12:58:02Z</recordCreationDate><recordChangeDate encoding="w3cdtf">2018-07-24T12:58:02Z</recordChangeDate>
</recordInfo>
</mods>