<mods xmlns:xlink="http://www.w3.org/1999/xlink" xmlns:xsi="http://www.w3.org/2001/XMLSchema-instance" xmlns="http://www.loc.gov/mods/v3" version="3.3" xsi:schemaLocation="http://www.loc.gov/mods/v3 http://www.loc.gov/standards/mods/v3/mods-3-3.xsd"><id>1983353</id><setSpec>journal_article</setSpec><setSpec>doc-type:article</setSpec><setSpec>ddc:150</setSpec><setSpec>journal_articleFtxt</setSpec><setSpec>open_access</setSpec>

<genre>article</genre>

<titleInfo><title>Neurolinguistic findings on the language lexicon: the special role of proper names</title></titleInfo>


<note type="publicationStatus">published</note>


<note type="qualityControlled">yes</note>

<name type="personal">
  <namePart type="given">Horst M.</namePart>
  <namePart type="family">Müller</namePart>
  <role><roleTerm type="text">author</roleTerm> </role><identifier type="local">11733</identifier><description xsi:type="identifierDefinition" type="orcid">0000-0001-7790-3556</description></name>







<name type="corporate">
  <namePart/>
  <identifier type="local">8014655</identifier>
  <role>
    <roleTerm type="text">department</roleTerm>
  </role>
</name>

<name type="corporate">
  <namePart/>
  <identifier type="local">7388525</identifier>
  <role>
    <roleTerm type="text">department</roleTerm>
  </role>
</name>









<relatedItem type="constituent">
  <location>
    <url displayLabel="Mueller-2010.pdf">https://pub.uni-bielefeld.de/download/1983353/2914301/Mueller-2010.pdf</url>
  </location>
  <physicalDescription><internetMediaType>application/pdf</internetMediaType></physicalDescription>
  <accessCondition type="restrictionOnAccess">no</accessCondition>
</relatedItem>
<originInfo><publisher>Chinese Physiological Society</publisher><dateIssued encoding="w3cdtf">2010</dateIssued>
</originInfo>
<language><languageTerm authority="iso639-2b" type="code">eng</languageTerm>
</language>



<relatedItem type="host"><titleInfo><title>Chinese Journal of Physiology</title></titleInfo>
  <identifier type="issn">0304-4920</identifier>
  <identifier type="MEDLINE">21793346</identifier>
  <identifier type="ISI">000285655500002</identifier><identifier type="urn">urn:nbn:de:0070-pub-19833536</identifier><identifier type="doi">10.4077/CJP.2010.AMM032</identifier>
<part><detail type="volume"><number>53</number></detail><detail type="issue"><number>6</number></detail><extent unit="pages">351-358</extent>
</part>
</relatedItem>


<extension>
<bibliographicCitation>
<chicago>&lt;div style="text-indent:-25px; padding-left:25px;padding-bottom:0px;"&gt;Müller, Horst M. 2010. “Neurolinguistic findings on the language lexicon: the special role of proper names”. &lt;em&gt;Chinese Journal of Physiology&lt;/em&gt; 53 (6): 351-358.&lt;/div&gt;</chicago>
<lncs> Müller, H.M.: Neurolinguistic findings on the language lexicon: the special role of proper names. Chinese Journal of Physiology. 53, 351-358 (2010).</lncs>
<default>Müller HM (2010) &lt;br /&gt;&lt;em&gt;Chinese Journal of Physiology&lt;/em&gt; 53(6): 351-358.</default>
<mla>Müller, Horst M. “Neurolinguistic findings on the language lexicon: the special role of proper names”. &lt;em&gt;Chinese Journal of Physiology&lt;/em&gt; 53.6 (2010): 351-358.</mla>
<wels>Müller, H. M. (2010): Neurolinguistic findings on the language lexicon: the special role of proper names &lt;em&gt;Chinese Journal of Physiology&lt;/em&gt;,53:(6): 351-358.</wels>
<angewandte-chemie>H. M.  Müller, “Neurolinguistic findings on the language lexicon: the special role of proper names”, &lt;em&gt;Chinese Journal of Physiology&lt;/em&gt;, &lt;strong&gt;2010&lt;/strong&gt;, &lt;em&gt;53&lt;/em&gt;, 351-358.</angewandte-chemie>
<bio1>Müller HM (2010) &lt;br /&gt;Neurolinguistic findings on the language lexicon: the special role of proper names.&lt;br /&gt;Chinese Journal of Physiology 53(6): 351-358.</bio1>
<harvard1>Müller, H.M., 2010. Neurolinguistic findings on the language lexicon: the special role of proper names. &lt;em&gt;Chinese Journal of Physiology&lt;/em&gt;, 53(6), p 351-358.</harvard1>
<apa_indent>&lt;div style="text-indent:-25px; padding-left:25px;padding-bottom:0px;"&gt;Müller, H. M. (2010). Neurolinguistic findings on the language lexicon: the special role of proper names. &lt;em&gt;Chinese Journal of Physiology&lt;/em&gt;, &lt;em&gt;53&lt;/em&gt;(6), 351-358. &lt;a href="https://doi.org/10.4077/CJP.2010.AMM032" target="_blank"&gt;https://doi.org/10.4077/CJP.2010.AMM032&lt;/a&gt;&lt;/div&gt;</apa_indent>
<dgps>&lt;div style="text-indent:-25px; padding-left:25px;padding-bottom:0px;"&gt;Müller, H.M. (2010). Neurolinguistic findings on the language lexicon: the special role of proper names. &lt;em&gt;Chinese Journal of Physiology&lt;/em&gt;, &lt;em&gt;53&lt;/em&gt;(6), 351-358. Chinese Physiological Society. doi:10.4077/CJP.2010.AMM032.&lt;/div&gt;</dgps>
<frontiers>Müller, H. M. (2010). Neurolinguistic findings on the language lexicon: the special role of proper names. &lt;em&gt;Chinese Journal of Physiology&lt;/em&gt; 53, 351-358.</frontiers>
<ama>Müller HM. Neurolinguistic findings on the language lexicon: the special role of proper names. &lt;em&gt;Chinese Journal of Physiology&lt;/em&gt;. 2010;53(6):351-358.</ama>
<ieee> H.M. Müller, “Neurolinguistic findings on the language lexicon: the special role of proper names”, &lt;em&gt;Chinese Journal of Physiology&lt;/em&gt;,  vol. 53, 2010,  pp. 351-358.</ieee>
<apa>Müller, H. M. (2010). Neurolinguistic findings on the language lexicon: the special role of proper names. &lt;em&gt;Chinese Journal of Physiology&lt;/em&gt;, &lt;em&gt;53&lt;/em&gt;(6), 351-358. &lt;a href="https://doi.org/10.4077/CJP.2010.AMM032" target="_blank"&gt;https://doi.org/10.4077/CJP.2010.AMM032&lt;/a&gt;</apa>
</bibliographicCitation>
</extension>
<recordInfo><recordIdentifier>1983353</recordIdentifier><recordCreationDate encoding="w3cdtf">2011-01-28T14:48:44Z</recordCreationDate><recordChangeDate encoding="w3cdtf">2018-07-24T12:59:52Z</recordChangeDate>
</recordInfo>
</mods>