<mods xmlns:xlink="http://www.w3.org/1999/xlink" xmlns:xsi="http://www.w3.org/2001/XMLSchema-instance" xmlns="http://www.loc.gov/mods/v3" version="3.3" xsi:schemaLocation="http://www.loc.gov/mods/v3 http://www.loc.gov/standards/mods/v3/mods-3-3.xsd"><id>2015855</id><setSpec>journal_article</setSpec><setSpec>doc-type:article</setSpec><setSpec>ddc:300</setSpec><setSpec>journal_articleFtxt</setSpec><setSpec>open_access</setSpec>

<genre>article</genre>

<titleInfo><title>Vereinbarkeit von Beruf und Familie. Neue Problemlagen und Herausforderungen</title></titleInfo>


<note type="publicationStatus">published</note>



<name type="personal">
  <namePart type="given">Mechtild</namePart>
  <namePart type="family">Oechsle-Grauvogel</namePart>
  <role><roleTerm type="text">author</roleTerm> </role><identifier type="local">157175</identifier></name>







<name type="corporate">
  <namePart/>
  <identifier type="local">10030</identifier>
  <role>
    <roleTerm type="text">department</roleTerm>
  </role>
</name>









<relatedItem type="constituent">
  <location>
    <url displayLabel="1221-Artikeltext-4537-1-10-20190208.pdf">https://pub.uni-bielefeld.de/download/2015855/2956755/1221-Artikeltext-4537-1-10-20190208.pdf</url>
  </location>
  <physicalDescription><internetMediaType>application/pdf</internetMediaType></physicalDescription>
  <accessCondition type="restrictionOnAccess">no</accessCondition>
</relatedItem>
<originInfo><publisher>Interdisziplinäres Zentrum für Frauen- und Geschlechterforschung (IFF) der Universität Bielefeld</publisher><dateIssued encoding="w3cdtf">2009</dateIssued>
</originInfo>
<language><languageTerm authority="iso639-2b" type="code">ger</languageTerm>
</language>



<relatedItem type="host"><titleInfo><title>IFFOnZeit. Onlinezeitschrift des Interdisziplinären Zentrums für Frauen- und Geschlechterforschung (IFF)</title></titleInfo>
  <identifier type="issn">1868-7156</identifier><identifier type="urn">urn:nbn:de:0070-pub-20158553</identifier><identifier type="doi">10.4119/izgonzeit-1221 </identifier>
<part><detail type="volume"><number>1</number></detail><detail type="issue"><number>1</number></detail><extent unit="pages">44-57</extent>
</part>
</relatedItem>


<extension>
<bibliographicCitation>
<apa>Oechsle-Grauvogel, M. (2009). Vereinbarkeit von Beruf und Familie. Neue Problemlagen und Herausforderungen. &lt;em&gt;IFFOnZeit. Onlinezeitschrift des Interdisziplinären Zentrums für Frauen- und Geschlechterforschung (IFF)&lt;/em&gt;, &lt;em&gt;1&lt;/em&gt;(1), 44-57. &lt;a href="https://doi.org/10.4119/izgonzeit-1221 " target="_blank"&gt;https://doi.org/10.4119/izgonzeit-1221 &lt;/a&gt;</apa>
<harvard1>Oechsle-Grauvogel, M., 2009. Vereinbarkeit von Beruf und Familie. Neue Problemlagen und Herausforderungen. &lt;em&gt;IFFOnZeit. Onlinezeitschrift des Interdisziplinären Zentrums für Frauen- und Geschlechterforschung (IFF)&lt;/em&gt;, 1(1), p 44-57.</harvard1>
<ieee> M. Oechsle-Grauvogel, “Vereinbarkeit von Beruf und Familie. Neue Problemlagen und Herausforderungen”, &lt;em&gt;IFFOnZeit. Onlinezeitschrift des Interdisziplinären Zentrums für Frauen- und Geschlechterforschung (IFF)&lt;/em&gt;,  vol. 1, 2009,  pp. 44-57.</ieee>
<default>Oechsle-Grauvogel M (2009) &lt;br /&gt;&lt;em&gt;IFFOnZeit. Onlinezeitschrift des Interdisziplinären Zentrums für Frauen- und Geschlechterforschung (IFF)&lt;/em&gt; 1(1): 44-57.</default>
<mla>Oechsle-Grauvogel, Mechtild. “Vereinbarkeit von Beruf und Familie. Neue Problemlagen und Herausforderungen”. &lt;em&gt;IFFOnZeit. Onlinezeitschrift des Interdisziplinären Zentrums für Frauen- und Geschlechterforschung (IFF)&lt;/em&gt; 1.1 (2009): 44-57.</mla>
<frontiers>Oechsle-Grauvogel, M. (2009). Vereinbarkeit von Beruf und Familie. Neue Problemlagen und Herausforderungen. &lt;em&gt;IFFOnZeit. Onlinezeitschrift des Interdisziplinären Zentrums für Frauen- und Geschlechterforschung (IFF)&lt;/em&gt; 1, 44-57.</frontiers>
<apa_indent>&lt;div style="text-indent:-25px; padding-left:25px;padding-bottom:0px;"&gt;Oechsle-Grauvogel, M. (2009). Vereinbarkeit von Beruf und Familie. Neue Problemlagen und Herausforderungen. &lt;em&gt;IFFOnZeit. Onlinezeitschrift des Interdisziplinären Zentrums für Frauen- und Geschlechterforschung (IFF)&lt;/em&gt;, &lt;em&gt;1&lt;/em&gt;(1), 44-57. &lt;a href="https://doi.org/10.4119/izgonzeit-1221 " target="_blank"&gt;https://doi.org/10.4119/izgonzeit-1221 &lt;/a&gt;&lt;/div&gt;</apa_indent>
<wels>Oechsle-Grauvogel, M. (2009): Vereinbarkeit von Beruf und Familie. Neue Problemlagen und Herausforderungen &lt;em&gt;IFFOnZeit. Onlinezeitschrift des Interdisziplinären Zentrums für Frauen- und Geschlechterforschung (IFF)&lt;/em&gt;,1:(1): 44-57.</wels>
<chicago>&lt;div style="text-indent:-25px; padding-left:25px;padding-bottom:0px;"&gt;Oechsle-Grauvogel, Mechtild. 2009. “Vereinbarkeit von Beruf und Familie. Neue Problemlagen und Herausforderungen”. &lt;em&gt;IFFOnZeit. Onlinezeitschrift des Interdisziplinären Zentrums für Frauen- und Geschlechterforschung (IFF)&lt;/em&gt; 1 (1): 44-57.&lt;/div&gt;</chicago>
<lncs> Oechsle-Grauvogel, M.: Vereinbarkeit von Beruf und Familie. Neue Problemlagen und Herausforderungen. IFFOnZeit. Onlinezeitschrift des Interdisziplinären Zentrums für Frauen- und Geschlechterforschung (IFF). 1, 44-57 (2009).</lncs>
<ama>Oechsle-Grauvogel M. Vereinbarkeit von Beruf und Familie. Neue Problemlagen und Herausforderungen. &lt;em&gt;IFFOnZeit. Onlinezeitschrift des Interdisziplinären Zentrums für Frauen- und Geschlechterforschung (IFF)&lt;/em&gt;. 2009;1(1):44-57.</ama>
<angewandte-chemie>M.  Oechsle-Grauvogel, “Vereinbarkeit von Beruf und Familie. Neue Problemlagen und Herausforderungen”, &lt;em&gt;IFFOnZeit. Onlinezeitschrift des Interdisziplinären Zentrums für Frauen- und Geschlechterforschung (IFF)&lt;/em&gt;, &lt;strong&gt;2009&lt;/strong&gt;, &lt;em&gt;1&lt;/em&gt;, 44-57.</angewandte-chemie>
<bio1>Oechsle-Grauvogel M (2009) &lt;br /&gt;Vereinbarkeit von Beruf und Familie. Neue Problemlagen und Herausforderungen.&lt;br /&gt;IFFOnZeit. Onlinezeitschrift des Interdisziplinären Zentrums für Frauen- und Geschlechterforschung (IFF) 1(1): 44-57.</bio1>
<dgps>&lt;div style="text-indent:-25px; padding-left:25px;padding-bottom:0px;"&gt;Oechsle-Grauvogel, M. (2009). Vereinbarkeit von Beruf und Familie. Neue Problemlagen und Herausforderungen. &lt;em&gt;IFFOnZeit. Onlinezeitschrift des Interdisziplinären Zentrums für Frauen- und Geschlechterforschung (IFF)&lt;/em&gt;, &lt;em&gt;1&lt;/em&gt;(1), 44-57. Interdisziplinäres Zentrum für Frauen- und Geschlechterforschung (IFF) der Universität Bielefeld. doi:10.4119/izgonzeit-1221 .&lt;/div&gt;</dgps>
</bibliographicCitation>
</extension>
<recordInfo><recordIdentifier>2015855</recordIdentifier><recordCreationDate encoding="w3cdtf">2011-03-10T09:26:59Z</recordCreationDate><recordChangeDate encoding="w3cdtf">2021-08-13T14:53:01Z</recordChangeDate>
</recordInfo>
</mods>