<mods xmlns:xlink="http://www.w3.org/1999/xlink" xmlns:xsi="http://www.w3.org/2001/XMLSchema-instance" xmlns="http://www.loc.gov/mods/v3" version="3.3" xsi:schemaLocation="http://www.loc.gov/mods/v3 http://www.loc.gov/standards/mods/v3/mods-3-3.xsd"><id>2497600</id><setSpec>conference</setSpec><setSpec>doc-type:conferenceObject</setSpec><setSpec>ddc:006</setSpec><setSpec>conferenceFtxt</setSpec><setSpec>open_access</setSpec>

<genre>conference paper</genre>

<titleInfo><title>Rules for an Ontology-based Approach to Adaptation</title></titleInfo>


<note type="publicationStatus">published</note>


<note type="qualityControlled">yes</note>

<name type="personal">
  <namePart type="given">Duc Thanh</namePart>
  <namePart type="family">Tran</namePart>
  <role><roleTerm type="text">author</roleTerm> </role></name>
<name type="personal">
  <namePart type="given">Philipp</namePart>
  <namePart type="family">Cimiano</namePart>
  <role><roleTerm type="text">author</roleTerm> </role><identifier type="local">15020699</identifier><description xsi:type="identifierDefinition" type="orcid">0000-0002-4771-441X</description></name>
<name type="personal">
  <namePart type="given">Anupriya</namePart>
  <namePart type="family">Ankolekar</namePart>
  <role><roleTerm type="text">author</roleTerm> </role></name>







<name type="corporate">
  <namePart/>
  <identifier type="local">15019923</identifier>
  <role>
    <roleTerm type="text">department</roleTerm>
  </role>
</name>



<name type="conference">
  <namePart>1st International Workshop on Semantic Media Adaptation and Personalization</namePart>
</name>







<relatedItem type="constituent">
  <location>
    <url displayLabel="Tran_Rules_for_an_On_1.pdf">https://pub.uni-bielefeld.de/download/2497600/2525225/Tran_Rules_for_an_On_1.pdf</url>
  </location>
  <physicalDescription><internetMediaType>application/pdf</internetMediaType></physicalDescription>
  <accessCondition type="restrictionOnAccess">no</accessCondition>
</relatedItem>
<originInfo><dateIssued encoding="w3cdtf">2006</dateIssued><place><placeTerm type="text">Athen, Greece</placeTerm></place>
</originInfo>
<language><languageTerm authority="iso639-2b" type="code">eng</languageTerm>
</language>



<relatedItem type="host"><titleInfo><title>Proceedings of the 1st International Workshop on Semantic Media Adaptation and Personalization</title></titleInfo><identifier type="urn">urn:nbn:de:0070-pub-24976002</identifier>
<part>
</part>
</relatedItem>


<extension>
<bibliographicCitation>
<default>Tran DT, Cimiano P, Ankolekar A (2006)  &lt;br /&gt;In:  Proceedings of the 1st International Workshop on Semantic Media Adaptation and Personalization.</default>
<mla>Tran, Duc Thanh, Cimiano, Philipp, and Ankolekar, Anupriya. “Rules for an Ontology-based Approach to Adaptation”. &lt;em&gt;Proceedings of the 1st International Workshop on Semantic Media Adaptation and Personalization&lt;/em&gt;. 2006.</mla>
<chicago>&lt;div style="text-indent:-25px; padding-left:25px;padding-bottom:0px;"&gt;Tran, Duc Thanh, Cimiano, Philipp, and Ankolekar, Anupriya. 2006. “Rules for an Ontology-based Approach to Adaptation”. In &lt;em&gt;Proceedings of the 1st International Workshop on Semantic Media Adaptation and Personalization&lt;/em&gt;.&lt;/div&gt;</chicago>
<lncs> Tran, D.T., Cimiano, P., Ankolekar, A.: Rules for an Ontology-based Approach to Adaptation. Proceedings of the 1st International Workshop on Semantic Media Adaptation and Personalization.  (2006).</lncs>
<ieee> D.T. Tran, P. Cimiano, and A. Ankolekar, “Rules for an Ontology-based Approach to Adaptation”, &lt;em&gt;Proceedings of the 1st International Workshop on Semantic Media Adaptation and Personalization&lt;/em&gt;, 2006.</ieee>
<apa>Tran, D. T., Cimiano, P., &amp;amp; Ankolekar, A. (2006). Rules for an Ontology-based Approach to Adaptation. &lt;em&gt;Proceedings of the 1st International Workshop on Semantic Media Adaptation and Personalization&lt;/em&gt;</apa>
<frontiers>Tran, D. T., Cimiano, P., and Ankolekar, A. (2006). “Rules for an Ontology-based Approach to Adaptation” in &lt;em&gt;Proceedings of the 1st International Workshop on Semantic Media Adaptation and Personalization&lt;/em&gt;.</frontiers>
<dgps>&lt;div style="text-indent:-25px; padding-left:25px;padding-bottom:0px;"&gt;Tran, D.T., Cimiano, P. &amp;amp; Ankolekar, A. (2006). Rules for an Ontology-based Approach to Adaptation. &lt;em&gt;Proceedings of the 1st International Workshop on Semantic Media Adaptation and Personalization&lt;/em&gt;. Gehalten auf der 1st International Workshop on Semantic Media Adaptation and Personalization.&lt;/div&gt;</dgps>
<ama>Tran DT, Cimiano P, Ankolekar A. Rules for an Ontology-based Approach to Adaptation. In:  &lt;em&gt;Proceedings of the 1st International Workshop on Semantic Media Adaptation and Personalization&lt;/em&gt;. 2006.</ama>
<angewandte-chemie>D. T.  Tran, P.  Cimiano, and A.  Ankolekar, in &lt;em&gt;Proceedings of the 1st International Workshop on Semantic Media Adaptation and Personalization&lt;/em&gt;, &lt;strong&gt;2006&lt;/strong&gt;.</angewandte-chemie>
<bio1>Tran DT, Cimiano P, Ankolekar A (2006) &lt;br /&gt;Rules for an Ontology-based Approach to Adaptation. &lt;br /&gt;In:  Proceedings of the 1st International Workshop on Semantic Media Adaptation and Personalization. .</bio1>
<harvard1>Tran, D.T., Cimiano, P., &amp;amp; Ankolekar, A., 2006. Rules for an Ontology-based Approach to Adaptation. In &lt;em&gt;Proceedings of the 1st International Workshop on Semantic Media Adaptation and Personalization&lt;/em&gt;.</harvard1>
<apa_indent>&lt;div style="text-indent:-25px; padding-left:25px;padding-bottom:0px;"&gt;Tran, D. T., Cimiano, P., &amp;amp; Ankolekar, A. (2006). Rules for an Ontology-based Approach to Adaptation. &lt;em&gt;Proceedings of the 1st International Workshop on Semantic Media Adaptation and Personalization&lt;/em&gt;&lt;/div&gt;</apa_indent>
<wels>Tran, D. T.; Cimiano, P.; Ankolekar, A. (2006): Rules for an Ontology-based Approach to Adaptation. In: Proceedings of the 1st International Workshop on Semantic Media Adaptation and Personalization.</wels>
</bibliographicCitation>
</extension>
<recordInfo><recordIdentifier>2497600</recordIdentifier><recordCreationDate encoding="w3cdtf">2012-05-16T10:26:35Z</recordCreationDate><recordChangeDate encoding="w3cdtf">2018-07-24T12:59:59Z</recordChangeDate>
</recordInfo>
</mods>