<mods xmlns:xlink="http://www.w3.org/1999/xlink" xmlns:xsi="http://www.w3.org/2001/XMLSchema-instance" xmlns="http://www.loc.gov/mods/v3" version="3.3" xsi:schemaLocation="http://www.loc.gov/mods/v3 http://www.loc.gov/standards/mods/v3/mods-3-3.xsd"><id>2914712</id><setSpec>journal_article</setSpec><setSpec>doc-type:article</setSpec><setSpec>ddc:370</setSpec><setSpec>journal_articleFtxt</setSpec><setSpec>open_access</setSpec>

<genre>article</genre>

<titleInfo><title>Adaptive Behavior System II - Eine erste Überprüfung der psychometrischen Eigenschaften der deutschen Erwachsenenversion</title></titleInfo>


<note type="publicationStatus">published</note>



<name type="personal">
  <namePart type="given">Carmen</namePart>
  <namePart type="family">Zurbriggen</namePart>
  <role><roleTerm type="text">author</roleTerm> </role><identifier type="local">68848711</identifier><description xsi:type="identifierDefinition" type="orcid">0000-0002-0906-2000</description></name>
<name type="personal">
  <namePart type="given">Dagmar</namePart>
  <namePart type="family">Orthmann Bless</namePart>
  <role><roleTerm type="text">author</roleTerm> </role></name>







<name type="corporate">
  <namePart/>
  <identifier type="local">7978223</identifier>
  <role>
    <roleTerm type="text">department</roleTerm>
  </role>
</name>









<relatedItem type="constituent">
  <location>
    <url displayLabel="JA_Zurbriggen_Orthmann-Bless_2017_ESP-9-1_3-18.pdf">https://pub.uni-bielefeld.de/download/2914712/2914749/JA_Zurbriggen_Orthmann-Bless_2017_ESP-9-1_3-18.pdf</url>
  </location>
  <physicalDescription><internetMediaType>application/pdf</internetMediaType></physicalDescription>
  <accessCondition type="restrictionOnAccess">no</accessCondition>
</relatedItem>
<originInfo><publisher>Pabst</publisher><dateIssued encoding="w3cdtf">2017</dateIssued>
</originInfo>
<language><languageTerm authority="iso639-2b" type="code">ger</languageTerm>
</language>



<relatedItem type="host"><titleInfo><title>Empirische Sonderpädagogik</title></titleInfo>
  <identifier type="issn">1869-4845</identifier><identifier type="urn">urn:nbn:de:0070-pub-29147129</identifier>
<part><detail type="volume"><number>9</number></detail><detail type="issue"><number>1</number></detail><extent unit="pages">3-18</extent>
</part>
</relatedItem>


<extension>
<bibliographicCitation>
<default>Zurbriggen C, Orthmann Bless D (2017) &lt;br /&gt;&lt;em&gt;Empirische Sonderpädagogik&lt;/em&gt; 9(1): 3-18.</default>
<mla>Zurbriggen, Carmen, and Orthmann Bless, Dagmar. “Adaptive Behavior System II - Eine erste Überprüfung der psychometrischen Eigenschaften der deutschen Erwachsenenversion”. &lt;em&gt;Empirische Sonderpädagogik&lt;/em&gt; 9.1 (2017): 3-18.</mla>
<frontiers>Zurbriggen, C., and Orthmann Bless, D. (2017). Adaptive Behavior System II - Eine erste Überprüfung der psychometrischen Eigenschaften der deutschen Erwachsenenversion. &lt;em&gt;Empirische Sonderpädagogik&lt;/em&gt; 9, 3-18.</frontiers>
<apa_indent>&lt;div style="text-indent:-25px; padding-left:25px;padding-bottom:0px;"&gt;Zurbriggen, C., &amp;amp; Orthmann Bless, D. (2017). Adaptive Behavior System II - Eine erste Überprüfung der psychometrischen Eigenschaften der deutschen Erwachsenenversion. &lt;em&gt;Empirische Sonderpädagogik&lt;/em&gt;, &lt;em&gt;9&lt;/em&gt;(1), 3-18.&lt;/div&gt;</apa_indent>
<wels>Zurbriggen, C.; Orthmann Bless, D. (2017): Adaptive Behavior System II - Eine erste Überprüfung der psychometrischen Eigenschaften der deutschen Erwachsenenversion &lt;em&gt;Empirische Sonderpädagogik&lt;/em&gt;,9:(1): 3-18.</wels>
<apa>Zurbriggen, C., &amp;amp; Orthmann Bless, D. (2017). Adaptive Behavior System II - Eine erste Überprüfung der psychometrischen Eigenschaften der deutschen Erwachsenenversion. &lt;em&gt;Empirische Sonderpädagogik&lt;/em&gt;, &lt;em&gt;9&lt;/em&gt;(1), 3-18.</apa>
<harvard1>Zurbriggen, C., &amp;amp; Orthmann Bless, D., 2017. Adaptive Behavior System II - Eine erste Überprüfung der psychometrischen Eigenschaften der deutschen Erwachsenenversion. &lt;em&gt;Empirische Sonderpädagogik&lt;/em&gt;, 9(1), p 3-18.</harvard1>
<ieee> C. Zurbriggen and D. Orthmann Bless, “Adaptive Behavior System II - Eine erste Überprüfung der psychometrischen Eigenschaften der deutschen Erwachsenenversion”, &lt;em&gt;Empirische Sonderpädagogik&lt;/em&gt;,  vol. 9, 2017,  pp. 3-18.</ieee>
<angewandte-chemie>C.  Zurbriggen, and D.  Orthmann Bless, “Adaptive Behavior System II - Eine erste Überprüfung der psychometrischen Eigenschaften der deutschen Erwachsenenversion”, &lt;em&gt;Empirische Sonderpädagogik&lt;/em&gt;, &lt;strong&gt;2017&lt;/strong&gt;, &lt;em&gt;9&lt;/em&gt;, 3-18.</angewandte-chemie>
<bio1>Zurbriggen C, Orthmann Bless D (2017) &lt;br /&gt;Adaptive Behavior System II - Eine erste Überprüfung der psychometrischen Eigenschaften der deutschen Erwachsenenversion.&lt;br /&gt;Empirische Sonderpädagogik 9(1): 3-18.</bio1>
<dgps>&lt;div style="text-indent:-25px; padding-left:25px;padding-bottom:0px;"&gt;Zurbriggen, C. &amp;amp; Orthmann Bless, D. (2017). Adaptive Behavior System II - Eine erste Überprüfung der psychometrischen Eigenschaften der deutschen Erwachsenenversion. &lt;em&gt;Empirische Sonderpädagogik&lt;/em&gt;, &lt;em&gt;9&lt;/em&gt;(1), 3-18. Pabst.&lt;/div&gt;</dgps>
<chicago>&lt;div style="text-indent:-25px; padding-left:25px;padding-bottom:0px;"&gt;Zurbriggen, Carmen, and Orthmann Bless, Dagmar. 2017. “Adaptive Behavior System II - Eine erste Überprüfung der psychometrischen Eigenschaften der deutschen Erwachsenenversion”. &lt;em&gt;Empirische Sonderpädagogik&lt;/em&gt; 9 (1): 3-18.&lt;/div&gt;</chicago>
<lncs> Zurbriggen, C., Orthmann Bless, D.: Adaptive Behavior System II - Eine erste Überprüfung der psychometrischen Eigenschaften der deutschen Erwachsenenversion. Empirische Sonderpädagogik. 9, 3-18 (2017).</lncs>
<ama>Zurbriggen C, Orthmann Bless D. Adaptive Behavior System II - Eine erste Überprüfung der psychometrischen Eigenschaften der deutschen Erwachsenenversion. &lt;em&gt;Empirische Sonderpädagogik&lt;/em&gt;. 2017;9(1):3-18.</ama>
</bibliographicCitation>
</extension>
<recordInfo><recordIdentifier>2914712</recordIdentifier><recordCreationDate encoding="w3cdtf">2017-10-24T20:33:57Z</recordCreationDate><recordChangeDate encoding="w3cdtf">2018-07-24T13:01:30Z</recordChangeDate>
</recordInfo>
</mods>